LICENSE
README.md
numerai_tools/__init__.py
numerai_tools/py.typed
numerai_tools/scoring.py
numerai_tools/signals.py
numerai_tools/submissions.py
numerai_tools-0.5.3.dist-info/METADATA
numerai_tools-0.5.3.dist-info/WHEEL
numerai_tools-0.5.3.dist-info/licenses/LICENSE
numerai_tools-0.5.3.dist-info/RECORD
