Metadata-Version: 2.4
Name: numerai-tools
Version: 0.5.3
Summary: A collection of open-source tools to help interact with Numerai, model data, and automate submissions.
License: MIT
License-File: LICENSE
Author: Numerai Engineering
Author-email: engineering@numer.ai
Requires-Python: >=3.11
Classifier: Development Status :: 5 - Production/Stable
Classifier: Environment :: Console
Classifier: Intended Audience :: Science/Research
Classifier: License :: OSI Approved :: MIT License
Classifier: Operating System :: OS Independent
Classifier: Programming Language :: Python
Classifier: Programming Language :: Python :: 3
Classifier: Topic :: Scientific/Engineering
Requires-Dist: numpy (>=2.0.0,<3.0.0)
Requires-Dist: pandas (>=2.2.2,<3.0.0)
Requires-Dist: scikit-learn (>=1.5.0,<2.0.0)
Requires-Dist: scipy (>=1.13.0,<2.0.0)
Project-URL: Documentation, https://docs.numer.ai/
Project-URL: Homepage, https://numer.ai
Project-URL: Repository, https://github.com/numerai/numerai-tools
